queueplus/__init__.py
queueplus/aioqueue.py
queueplus/datatypes.py
queueplus/logger.py
queueplus/violations.py
queueplus-0.7.0.dist-info/METADATA
queueplus-0.7.0.dist-info/WHEEL
queueplus-0.7.0.dist-info/top_level.txt
queueplus-0.7.0.dist-info/RECORD
