Metadata-Version: 2.1
Name: queueplus
Version: 0.7.0
Summary: A Python library that adds functionality to asyncio queues
Home-page: https://github.com/mitchelllisle/queueplus
Author: Mitchell Lisle
Author-email: m.lisle90@gmail.com
License: MIT license
Keywords: queueplus
Requires-Dist: bloom-filter
